[
  {
    "type": "Semaine du:",
    "info1": "19/05/25",
    "info2": "23/05/25"
  },
  {
    "type": "Lundi",
    "info1": "Salade de radis, concombre et pommes de terre",
    "info2": "Risotto à la poire, gorgonzola et noix"
  },
  {
    "type": "Mardi",
    "info1": "Tartare de bœuf à la mozzarella di buffala",
    "info2": "Escalope de poulet tomate mozzarella et potatoes maison"
  },
  {
    "type": "Mercredi",
    "info1": "Focaccia à l’orientale",
    "info2": "Vittelo tonnato et salade caprèse"
  },
  {
    "type": "Jeudi",
    "info1": "Bruschetta au pesto, chèvre et tomate",
    "info2": "Polpettes Napoli et pasta"
  },
  {
    "type": "Vendredi",
    "info1": "Carpaccio de melon, saumon fumé, et burrata",
    "info2": "Filet de poisson sur écrasé de pommes de terre et carottes"
  },
  {
    "type": "Dessert:",
    "info1": "Verrine mangue et spéculoos",
    "info2": ""
  },
  {
    "type": "Cheesecake:",
    "info1": "A la pistache",
    "info2": ""
  }
]
