[
  {
    "type": "Semaine du:",
    "info1": "07/04",
    "info2": "11/04/25"
  },
  {
    "type": "Lundi",
    "info1": "Tartare de bœuf",
    "info2": "Pasta girasoli farcie, sauce tomate à la truffe et ricottta"
  },
  {
    "type": "Mardi",
    "info1": "Salade de Panzanella (salade Toscane)",
    "info2": "Brochettes de boeuf, frites maison et salade"
  },
  {
    "type": "Mercredi",
    "info1": "Toasts de crème de feta à la betterave",
    "info2": "Saltimbocca alla Romana et linguines"
  },
  {
    "type": "Jeudi",
    "info1": "Salade de poulet à la mexicaine",
    "info2": "Gnocchis alla Sorrentina"
  },
  {
    "type": "Vendredi",
    "info1": "Saumon gravlax",
    "info2": "Filet de sole à la provençale et son risotto"
  },
  {
    "type": "Dessert:",
    "info1": "Mousse de mascarpone à la fraise",
    "info2": ""
  },
  {
    "type": "Cheesecake:",
    "info1": "Aux Framboises",
    "info2": ""
  }
]
